{"index":"ancient-green-dragon","name":"ANCIENT_GREEN_DRAGON","size":"GARGANTUAN","type":"DRAGON","subtype":null,"alignment":"LAWFUL_EVIL","hit_points":385,"hit_dice":"22d20","hit_points_roll":"22d20+154","challenge_rating":22.0,"strength":27,"dexterity":12,"constitution":25,"intelligence":20,"wisdom":17,"charisma":19,"xp":41000,"damage_vulnerabilities":[],"damage_resistances":[],"damage_immunities":["POISON"],"condition_immunities":[{"name":"POISONED"}],"languages":"Common, Draconic","image":"/api/images/monsters/ancient-green-dragon.png","challengeRatingFormatted":"22","challengeRatingStars":"★★★★★"}