{"index":"gray-ooze","name":"GRAY_OOZE","size":"MEDIUM","type":"OOZE","subtype":null,"alignment":"UNALIGNED","hit_points":22,"hit_dice":"3d8","hit_points_roll":"3d8+9","challenge_rating":0.5,"strength":12,"dexterity":6,"constitution":16,"intelligence":1,"wisdom":6,"charisma":2,"xp":100,"damage_vulnerabilities":[],"damage_resistances":["ACID","COLD","FIRE"],"damage_immunities":[],"condition_immunities":[{"name":"BLINDED"},{"name":"CHARMED"},{"name":"DEAFENED"},{"name":"EXHAUSTION"},{"name":"FRIGHTENED"},{"name":"PRONE"}],"languages":"","image":"/api/images/monsters/gray-ooze.png","challengeRatingFormatted":"1/2","challengeRatingStars":"★"}